{
    "version": "1.0.3",
    "architecture": {
        "64bit": {
            "url": "https://github.com/JetBrains/qodana-cli/releases/download/v1.0.3/qodana_windows_x86_64.zip",
            "bin": [
                "qodana.exe"
            ],
            "hash": "8114ef44f3549fcd7db7dac58179b63847d7adabe40fd58b7bef1610fdc6d605"
        }
    },
    "homepage": "https://github.com/JetBrains/qodana-cli",
    "license": "Apache-2.0",
    "description": "🔧 Run Qodana as fast as possible, with minimum effort required"
}