{
    "version": "2025.3.2",
    "architecture": {
        "64bit": {
            "url": "https://github.com/JetBrains/qodana-cli/releases/download/v2025.3.2/qodana_windows_x86_64.zip",
            "bin": [
                "qodana.exe"
            ],
            "hash": "f536d158ca4d3a7af17f9bebe3210a22e0fb664910ac31e91813898dbafd7dea"
        },
        "arm64": {
            "url": "https://github.com/JetBrains/qodana-cli/releases/download/v2025.3.2/qodana_windows_arm64.zip",
            "bin": [
                "qodana.exe"
            ],
            "hash": "6fe4e2add0880ef910d248f2896df1d6421661dd25f6e6813fa2f8c1a3180db7"
        }
    },
    "homepage": "https://github.com/JetBrains/qodana-cli",
    "license": "Apache-2.0",
    "description": "🔧 Run Qodana as fast as possible, with minimum effort required"
}
