{
    "version": "0.7.3",
    "architecture": {
        "64bit": {
            "url": "https://github.com/JetBrains/qodana-cli/releases/download/v0.7.3/qodana_0.7.3_windows_x86_64.tar.gz",
            "bin": [
                "qodana.exe"
            ],
            "hash": "fefca758cff679810ee63d473f076f73d4550a713473df47b08708be01e96b06"
        }
    },
    "homepage": "https://github.com/JetBrains/qodana-cli",
    "license": "Apache-2.0",
    "description": "🔧 Run Qodana as fast as possible, with minimum effort required"
}